[{"player_info": {"overall": "83", "short_name": "T. Alderweireld", "full_name": "Toby Alderweireld", "position": "CB", "img_url": "https://cdn.sofifa.net/players/184/087/22_180.png", "country": "Belgium", "so_country": "https://cdn.sofifa.net/pixel.gif", "club_url": "https://cdn.sofifa.net/flags/be@3x.png", "club": "", "player_id": "184087"}, "list_of_team_mates": ["190460", "143745", "177358", "235569"]}, {"player_info": {"overall": "82", "short_name": "I. Peri\u0161i\u0107", "full_name": "Ivan Peri\u0161i\u0107", "position": "LM", "img_url": "https://cdn.sofifa.net/players/181/458/22_180.png", "country": "Croatia", "so_country": "https://cdn.sofifa.net/pixel.gif", "club_url": "https://cdn.sofifa.net/teams/44/90.png", "club": "Inter", "player_id": "181458"}, "list_of_team_mates": ["183556", "192985", "231478", "189596"]}, {"player_info": {"overall": "83", "short_name": "S. Kj\u00e6r", "full_name": "Simon Kj\u00e6r", "position": "CB", "img_url": "https://cdn.sofifa.net/players/179/645/22_180.png", "country": "Denmark", "so_country": "https://cdn.sofifa.net/pixel.gif", "club_url": "https://cdn.sofifa.net/teams/47/90.png", "club": "AC Milan", "player_id": "179645"}, "list_of_team_mates": ["053116", "171919", "053302", "139968", "166706", "207471", "241721"]}, {"player_info": {"overall": "85", "short_name": "Reina", "full_name": " Reina", "position": "GK", "img_url": "https://cdn.sofifa.net/players/024/630/09_180.png", "country": "Spain", "so_country": "https://cdn.sofifa.net/pixel.gif", "club_url": "https://cdn.sofifa.net/teams/9/90.png", "club": "Liverpool", "player_id": "024630"}, "list_of_team_mates": ["015723", "157481", "183907", "219809", "198706"]}, {"player_info": {"overall": "92", "short_name": "R. Lukaku", "full_name": "Romelu Lukaku", "position": "ST", "img_url": "https://cdn.sofifa.net/players/192/505/22_180.png", "country": "Belgium", "so_country": "https://cdn.sofifa.net/pixel.gif", "club_url": "https://cdn.sofifa.net/teams/5/90.png", "club": "Chelsea", "player_id": "192505"}, "list_of_team_mates": ["205498", "193474", "207494", "190460"]}, {"player_info": {"overall": "82", "short_name": "L. Muriel", "full_name": "Luis Muriel", "position": "ST", "img_url": "https://cdn.sofifa.net/players/199/110/22_180.png", "country": "Colombia", "so_country": "https://cdn.sofifa.net/flags/co.png", "club_url": "https://cdn.sofifa.net/teams/39/90.png", "club": "Atalanta", "player_id": "199110"}, "list_of_team_mates": ["177509", "168354", "204277", "215333"]}, {"player_info": {"overall": "91", "short_name": "D. Berbatov", "full_name": "Dimitar Berbatov", "position": "ST", "img_url": "https://cdn.sofifa.net/players/030/110/09_180.png", "country": "Bulgaria", "so_country": "https://cdn.sofifa.net/pixel.gif", "club_url": "https://cdn.sofifa.net/teams/11/90.png", "club": "Manchester United", "player_id": "030110"}, "list_of_team_mates": ["167963", "046815", "162347", "120312"]}, {"player_info": {"overall": "92", "short_name": "Jo\u00e3o Cancelo", "full_name": "Jo\u00e3o Pedro Cavaco Cancelo", "position": "LB", "img_url": "https://cdn.sofifa.net/players/210/514/22_180.png", "country": "Portugal", "so_country": "https://cdn.sofifa.net/pixel.gif", "club_url": "https://cdn.sofifa.net/teams/10/90.png", "club": "Manchester City", "player_id": "210514"}, "list_of_team_mates": ["139068", "162835", "190483", "186942"]}, {"player_info": {"overall": "83", "short_name": "L. Podolski", "full_name": "Lukas Podolski", "position": "ST", "img_url": "https://cdn.sofifa.net/players/150/516/09_180.png", "country": "Germany", "so_country": "https://cdn.sofifa.net/pixel.gif", "club_url": "https://cdn.sofifa.net/teams/21/90.png", "club": "FC Bayern M\u00fcnchen", "player_id": "150516"}, "list_of_team_mates": ["053612", "140601", "182494", "000041", "019765"]}, {"player_info": {"overall": "84", "short_name": "Andr\u00e9 Silva", "full_name": "Andr\u00e9 Miguel Valente da Silva", "position": "ST", "img_url": "https://cdn.sofifa.net/players/228/941/22_180.png", "country": "Portugal", "so_country": "https://cdn.sofifa.net/pixel.gif", "club_url": "https://cdn.sofifa.net/teams/112172/90.png", "club": "RB Leipzig", "player_id": "228941"}, "list_of_team_mates": ["184267", "208128", "199451", "188943", "208448"]}, {"player_info": {"overall": "84", "short_name": "L. Digne", "full_name": "Lucas Digne", "position": "LB", "img_url": "https://cdn.sofifa.net/players/200/458/22_180.png", "country": "France", "so_country": "https://cdn.sofifa.net/pixel.gif", "club_url": "https://cdn.sofifa.net/teams/2/90.png", "club": "Aston Villa", "player_id": "200458"}, "list_of_team_mates": ["150656", "179944", "180206", "176580", "199914", "189242"]}, {"player_info": {"overall": "82", "short_name": "I. Peri\u0161i\u0107", "full_name": "Ivan Peri\u0161i\u0107", "position": "LM", "img_url": "https://cdn.sofifa.net/players/181/458/22_180.png", "country": "Croatia", "so_country": "https://cdn.sofifa.net/pixel.gif", "club_url": "https://cdn.sofifa.net/teams/44/90.png", "club": "Inter", "player_id": "181458"}, "list_of_team_mates": ["178603", "171919", "198176", "177610"]}, {"player_info": {"overall": "86", "short_name": "Paulinho", "full_name": "Jos\u00e9 Paulo Bezerra M. J\u00fanior", "position": "CM", "img_url": "https://cdn.sofifa.net/players/187/961/20_180.png", "country": "Brazil", "so_country": "https://cdn.sofifa.net/pixel.gif", "club_url": "https://cdn.sofifa.net/teams/111839/90.png", "club": "Guangzhou FC", "player_id": "187961"}, "list_of_team_mates": ["180175", "167948", "031432", "205600", "212523"]}, {"player_info": {"overall": "83", "short_name": "G. Higua\u00edn", "full_name": "Gonzalo Higua\u00edn", "position": "ST", "img_url": "https://cdn.sofifa.net/players/167/664/09_180.png", "country": "Argentina", "so_country": "https://cdn.sofifa.net/pixel.gif", "club_url": "https://cdn.sofifa.net/teams/243/90.png", "club": "Real Madrid CF", "player_id": "167664"}, "list_of_team_mates": ["045574", "199914", "191043", "184432"]}, {"player_info": {"overall": "91", "short_name": "Z. Ibrahimovi\u0107", "full_name": "Zlatan Ibrahimovi\u0107", "position": "ST", "img_url": "https://cdn.sofifa.net/players/041/236/09_180.png", "country": "Sweden", "so_country": "https://cdn.sofifa.net/flags/se.png", "club_url": "https://cdn.sofifa.net/teams/44/90.png", "club": "Inter", "player_id": "041236"}, "list_of_team_mates": ["010535", "230938", "168435", "190815", "016619"]}, {"player_info": {"overall": "85", "short_name": "Reina", "full_name": " Reina", "position": "GK", "img_url": "https://cdn.sofifa.net/players/024/630/09_180.png", "country": "Spain", "so_country": "https://cdn.sofifa.net/pixel.gif", "club_url": "https://cdn.sofifa.net/teams/9/90.png", "club": "Liverpool", "player_id": "024630"}, "list_of_team_mates": ["157301", "175943", "009014", "189125", "223848"]}, {"player_info": {"overall": "86", "short_name": "M. Benatia", "full_name": "Medhi Benatia", "position": "CB", "img_url": "https://cdn.sofifa.net/players/177/509/18_180.png", "country": "Morocco", "so_country": "https://cdn.sofifa.net/pixel.gif", "club_url": "https://cdn.sofifa.net/teams/45/90.png", "club": "Juventus", "player_id": "177509"}, "list_of_team_mates": ["120274", "001238", "197445", "173210"]}, {"player_info": {"overall": "82", "short_name": "Nani", "full_name": " Nani", "position": "LW", "img_url": "https://cdn.sofifa.net/players/139/068/09_180.png", "country": "Portugal", "so_country": "https://cdn.sofifa.net/pixel.gif", "club_url": "https://cdn.sofifa.net/teams/11/90.png", "club": "Manchester United", "player_id": "139068"}, "list_of_team_mates": ["012265", "148302", "007826", "192492", "198176"]}, {"player_info": {"overall": "91", "short_name": "S. Eto'o", "full_name": "Samuel Eto'o", "position": "ST", "img_url": "https://cdn.sofifa.net/players/009/676/09_180.png", "country": "Cameroon", "so_country": "https://cdn.sofifa.net/pixel.gif", "club_url": "https://cdn.sofifa.net/teams/241/90.png", "club": "FC Barcelona", "player_id": "009676"}, "list_of_team_mates": ["023461", "164435", "180403", "045472"]}, {"player_info": {"overall": "82", "short_name": "Coutinho", "full_name": "Philippe Coutinho Correia", "position": "CAM", "img_url": "https://cdn.sofifa.net/players/189/242/22_180.png", "country": "Brazil", "so_country": "https://cdn.sofifa.net/pixel.gif", "club_url": "https://cdn.sofifa.net/teams/2/90.png", "club": "Aston Villa", "player_id": "189242"}, "list_of_team_mates": ["137361", "197061", "194404", "188545", "229906"]}, {"player_info": {"overall": "83", "short_name": "L. Podolski", "full_name": "Lukas Podolski", "position": "ST", "img_url": "https://cdn.sofifa.net/players/150/516/09_180.png", "country": "Germany", "so_country": "https://cdn.sofifa.net/pixel.gif", "club_url": "https://cdn.sofifa.net/teams/21/90.png", "club": "FC Bayern M\u00fcnchen", "player_id": "150516"}, "list_of_team_mates": ["165229", "193532", "139869", "000041", "023015"]}, {"player_info": {"overall": "92", "short_name": "R. Lukaku", "full_name": "Romelu Lukaku", "position": "ST", "img_url": "https://cdn.sofifa.net/players/192/505/22_180.png", "country": "Belgium", "so_country": "https://cdn.sofifa.net/pixel.gif", "club_url": "https://cdn.sofifa.net/teams/5/90.png", "club": "Chelsea", "player_id": "192505"}, "list_of_team_mates": ["207410", "163631", "207494", "181458"]}, {"player_info": {"overall": "84", "short_name": "Fernando", "full_name": "Fernando Reges Mouta", "position": "CDM", "img_url": "https://cdn.sofifa.net/players/184/134/22_180.png", "country": "Brazil", "so_country": "https://cdn.sofifa.net/pixel.gif", "club_url": "https://cdn.sofifa.net/teams/481/90.png", "club": "Sevilla FC", "player_id": "184134"}, "list_of_team_mates": ["190531", "186942", "182494", "219693"]}, {"player_info": {"overall": "83", "short_name": "T. Alderweireld", "full_name": "Toby Alderweireld", "position": "CB", "img_url": "https://cdn.sofifa.net/players/184/087/22_180.png", "country": "Belgium", "so_country": "https://cdn.sofifa.net/pixel.gif", "club_url": "https://cdn.sofifa.net/flags/be@3x.png", "club": "", "player_id": "184087"}, "list_of_team_mates": ["190460", "193747", "177358", "220793"]}, {"player_info": {"overall": "91", "short_name": "D. Berbatov", "full_name": "Dimitar Berbatov", "position": "ST", "img_url": "https://cdn.sofifa.net/players/030/110/09_180.png", "country": "Bulgaria", "so_country": "https://cdn.sofifa.net/pixel.gif", "club_url": "https://cdn.sofifa.net/teams/11/90.png", "club": "Manchester United", "player_id": "030110"}, "list_of_team_mates": ["139068", "169808", "112253", "120312"]}, {"player_info": {"overall": "84", "short_name": "Andr\u00e9 Silva", "full_name": "Andr\u00e9 Miguel Valente da Silva", "position": "ST", "img_url": "https://cdn.sofifa.net/players/228/941/22_180.png", "country": "Portugal", "so_country": "https://cdn.sofifa.net/pixel.gif", "club_url": "https://cdn.sofifa.net/teams/112172/90.png", "club": "RB Leipzig", "player_id": "228941"}, "list_of_team_mates": ["207863", "158963", "146536", "208574", "185122"]}, {"player_info": {"overall": "82", "short_name": "G. Rossi", "full_name": "Giuseppe Rossi", "position": "CF", "img_url": "https://cdn.sofifa.net/players/162/409/09_180.png", "country": "Italy", "so_country": "https://cdn.sofifa.net/pixel.gif", "club_url": "https://cdn.sofifa.net/teams/483/90.png", "club": "Villarreal CF", "player_id": "162409"}, "list_of_team_mates": ["001605", "161956", "192629", "198009"]}, {"player_info": {"overall": "85", "short_name": "R. van Persie", "full_name": "Robin van Persie", "position": "CF", "img_url": "https://cdn.sofifa.net/players/007/826/09_180.png", "country": "Netherlands", "so_country": "https://cdn.sofifa.net/pixel.gif", "club_url": "https://cdn.sofifa.net/teams/1/90.png", "club": "Arsenal", "player_id": "007826"}, "list_of_team_mates": ["163419", "054050", "179645"]}, {"player_info": {"overall": "86", "short_name": "D. Zapata", "full_name": "Duv\u00e1n Zapata", "position": "ST", "img_url": "https://cdn.sofifa.net/players/215/333/22_180.png", "country": "Colombia", "so_country": "https://cdn.sofifa.net/pixel.gif", "club_url": "https://cdn.sofifa.net/teams/39/90.png", "club": "Atalanta", "player_id": "215333"}, "list_of_team_mates": ["171877", "183497", "168354", "223273"]}, {"player_info": {"overall": "85", "short_name": "Quaresma", "full_name": " Quaresma", "position": "RW", "img_url": "https://cdn.sofifa.net/players/020/775/09_180.png", "country": "Portugal", "so_country": "https://cdn.sofifa.net/pixel.gif", "club_url": "https://cdn.sofifa.net/teams/5/90.png", "club": "Chelsea", "player_id": "020775"}, "list_of_team_mates": ["009676", "177491", "020170", "136130"]}, {"player_info": {"overall": "92", "short_name": "M. Salah", "full_name": "Mohamed Salah", "position": "RW", "img_url": "https://cdn.sofifa.net/players/209/331/22_180.png", "country": "Egypt", "so_country": "https://cdn.sofifa.net/flags/eg.png", "club_url": "https://cdn.sofifa.net/teams/9/90.png", "club": "Liverpool", "player_id": "209331"}, "list_of_team_mates": ["184943", "162409", "189712", "203376"]}, {"player_info": {"overall": "86", "short_name": "M. Depay", "full_name": "Memphis Depay", "position": "CF", "img_url": "https://cdn.sofifa.net/players/202/556/22_180.png", "country": "Netherlands", "so_country": "https://cdn.sofifa.net/pixel.gif", "club_url": "https://cdn.sofifa.net/teams/241/90.png", "club": "FC Barcelona", "player_id": "202556"}, "list_of_team_mates": ["193080", "234906", "228702"]}, {"player_info": {"overall": "85", "short_name": "M. Gomez", "full_name": "Mario Gomez", "position": "ST", "img_url": "https://cdn.sofifa.net/players/150/418/09_180.png", "country": "Germany", "so_country": "https://cdn.sofifa.net/pixel.gif", "club_url": "https://cdn.sofifa.net/teams/36/90.png", "club": "VfB Stuttgart", "player_id": "150418"}, "list_of_team_mates": ["156616", "161956", "196934", "185221"]}, {"player_info": {"overall": "83", "short_name": "S. Haller", "full_name": "S\u00e9bastien Haller", "position": "ST", "img_url": "https://cdn.sofifa.net/players/205/693/22_180.png", "country": "C\u00f4te d'Ivoire", "so_country": "https://cdn.sofifa.net/pixel.gif", "club_url": "https://cdn.sofifa.net/teams/245/90.png", "club": "Ajax", "player_id": "205693"}, "list_of_team_mates": ["232432", "164835", "190815"]}, {"player_info": {"overall": "92", "short_name": "C. Immobile", "full_name": "Ciro Immobile", "position": "ST", "img_url": "https://cdn.sofifa.net/players/192/387/22_180.png", "country": "Italy", "so_country": "https://cdn.sofifa.net/pixel.gif", "club_url": "https://cdn.sofifa.net/teams/46/90.png", "club": "Lazio", "player_id": "192387"}, "list_of_team_mates": ["210282", "002196", "198706"]}, {"player_info": {"overall": "86", "short_name": "Paulinho", "full_name": "Jos\u00e9 Paulo Bezerra M. J\u00fanior", "position": "CM", "img_url": "https://cdn.sofifa.net/players/187/961/20_180.png", "country": "Brazil", "so_country": "https://cdn.sofifa.net/pixel.gif", "club_url": "https://cdn.sofifa.net/teams/111839/90.png", "club": "Guangzhou FC", "player_id": "187961"}, "list_of_team_mates": ["180175", "172871", "177413", "158023", "212523"]}, {"player_info": {"overall": "86", "short_name": "M. Mand\u017euki\u0107", "full_name": "Mario Mand\u017euki\u0107", "position": "ST", "img_url": "https://cdn.sofifa.net/players/181/783/19_180.png", "country": "Croatia", "so_country": "https://cdn.sofifa.net/pixel.gif", "club_url": "https://cdn.sofifa.net/teams/45/90.png", "club": "Juventus", "player_id": "181783"}, "list_of_team_mates": ["007518", "121944", "143745", "138956"]}, {"player_info": {"overall": "83", "short_name": "G. Higua\u00edn", "full_name": "Gonzalo Higua\u00edn", "position": "ST", "img_url": "https://cdn.sofifa.net/players/167/664/09_180.png", "country": "Argentina", "so_country": "https://cdn.sofifa.net/pixel.gif", "club_url": "https://cdn.sofifa.net/teams/243/90.png", "club": "Real Madrid CF", "player_id": "167664"}, "list_of_team_mates": ["148803", "171877", "186561", "189505"]}, {"player_info": {"overall": "91", "short_name": "David Villa", "full_name": " David Villa", "position": "ST", "img_url": "https://cdn.sofifa.net/players/113/422/09_180.png", "country": "Spain", "so_country": "https://cdn.sofifa.net/pixel.gif", "club_url": "https://cdn.sofifa.net/teams/461/90.png", "club": "Valencia CF", "player_id": "113422"}, "list_of_team_mates": ["111010", "010535", "168609", "000041"]}, {"player_info": {"overall": "86", "short_name": "P. Aubameyang", "full_name": "Pierre-Emerick Aubameyang", "position": "ST", "img_url": "https://cdn.sofifa.net/players/188/567/22_180.png", "country": "Gabon", "so_country": "https://cdn.sofifa.net/pixel.gif", "club_url": "https://cdn.sofifa.net/teams/241/90.png", "club": "FC Barcelona", "player_id": "188567"}, "list_of_team_mates": ["167628", "231443", "192563", "251854"]}, {"player_info": {"overall": "83", "short_name": "Naldo", "full_name": " Naldo", "position": "CB", "img_url": "https://cdn.sofifa.net/players/171/919/09_180.png", "country": "Brazil", "so_country": "https://cdn.sofifa.net/pixel.gif", "club_url": "https://cdn.sofifa.net/teams/38/90.png", "club": "SV Werder Bremen", "player_id": "171919"}, "list_of_team_mates": ["025420", "183574", "209658", "227055"]}, {"player_info": {"overall": "92", "short_name": "Bruno Fernandes", "full_name": "Bruno Miguel Borges Fernandes", "position": "CAM", "img_url": "https://cdn.sofifa.net/players/212/198/22_180.png", "country": "Portugal", "so_country": "https://cdn.sofifa.net/pixel.gif", "club_url": "https://cdn.sofifa.net/teams/11/90.png", "club": "Manchester United", "player_id": "212198"}, "list_of_team_mates": ["168354", "112316", "193080"]}, {"player_info": {"overall": "83", "short_name": "J. Cuadrado", "full_name": "Juan Cuadrado", "position": "RB", "img_url": "https://cdn.sofifa.net/players/193/082/22_180.png", "country": "Colombia", "so_country": "https://cdn.sofifa.net/flags/co.png", "club_url": "https://cdn.sofifa.net/teams/45/90.png", "club": "Juventus", "player_id": "193082"}, "list_of_team_mates": ["162409", "184432", "201153"]}, {"player_info": {"overall": "82", "short_name": "R. Babel", "full_name": "Ryan Babel", "position": "LW", "img_url": "https://cdn.sofifa.net/players/157/301/09_180.png", "country": "Netherlands", "so_country": "https://cdn.sofifa.net/pixel.gif", "club_url": "https://cdn.sofifa.net/teams/9/90.png", "club": "Liverpool", "player_id": "157301"}, "list_of_team_mates": ["152039", "190815", "020775"]}, {"player_info": {"overall": "85", "short_name": "A. Cassano", "full_name": "Antonio Cassano", "position": "CF", "img_url": "https://cdn.sofifa.net/players/007/631/09_180.png", "country": "Italy", "so_country": "https://cdn.sofifa.net/pixel.gif", "club_url": "https://cdn.sofifa.net/teams/1837/90.png", "club": "U.C. Sampdoria", "player_id": "007631"}, "list_of_team_mates": ["052829", "001088", "142708", "001183"]}]